taichi_glsl/__init__.py
taichi_glsl/classes.py
taichi_glsl/colormap.py
taichi_glsl/experimental_array.py
taichi_glsl/experimental_cfd.py
taichi_glsl/experimental_transform.py
taichi_glsl/gui.py
taichi_glsl/hack.py
taichi_glsl/lagrangian.py
taichi_glsl/mkimages.py
taichi_glsl/odop.py
taichi_glsl/painting.py
taichi_glsl/randgen.py
taichi_glsl/sampling.py
taichi_glsl/scalar.py
taichi_glsl/sphcore.py
taichi_glsl/vector.py
taichi_glsl/version.py
taichi_glsl-0.0.12.dist-info/METADATA
taichi_glsl-0.0.12.dist-info/WHEEL
taichi_glsl-0.0.12.dist-info/top_level.txt
taichi_glsl-0.0.12.dist-info/RECORD
