Metadata-Version: 2.1
Name: taichi-glsl
Version: 0.0.12
Summary: A Taichi extension library providing a set of GLSL-alike helper functions
Home-page: UNKNOWN
Author: 彭于斌
Author-email: 1931127624@qq.com
License: UNKNOWN
Platform: UNKNOWN
Classifier: Intended Audience :: Developers
Classifier: Intended Audience :: Science/Research
Classifier: Topic :: Multimedia :: Graphics
Classifier: Topic :: Games/Entertainment :: Simulation
Classifier: Operating System :: OS Independent
Requires-Python: >=3.6
Requires-Dist: taichi (>=0.9.0)
